setup.py
speech_ml/__init__.py
speech_ml/data_names.py
speech_ml/data_sources.py
speech_ml/kbhit.py
speech_ml/keras_generators.py
speech_ml/learning.py
speech_ml/lookup_tables.py
speech_ml/util.py
speech_ml/waveform_tools.py
speech_ml/yaml_util.py
speech_ml.egg-info/PKG-INFO
speech_ml.egg-info/SOURCES.txt
speech_ml.egg-info/dependency_links.txt
speech_ml.egg-info/requires.txt
speech_ml.egg-info/top_level.txt