Metadata-Version: 1.1
Name: speech-ml
Version: 0.0.1
Summary: Deep Learning utilities for audio using keras
Home-page: https://github.com/coopie/speech_ml
Author: Sam Coope
Author-email: sam.j.coope@gmail.com
License: MIT
Download-URL: https://github.com/coopie/speech_ml/archive/master.zip
Platform: UNKNOWN
